transcription-burato/__init__.py
transcription-burato/io.py
transcription-burato/process.py
transcription_burato/__init__.py
transcription_burato/io.py
transcription_burato/process.py
transcription_burato-0.0.2.dist-info/METADATA
transcription_burato-0.0.2.dist-info/WHEEL
transcription_burato-0.0.2.dist-info/top_level.txt
transcription_burato-0.0.2.dist-info/RECORD
