Metadata-Version: 2.1
Name: transcription-burato
Version: 0.0.2
Summary: A simples program that transcribes dna
Home-page: https://github.com/Otavio-Burato/DNA
Author: Otavio Burato de Oliveira
Author-email: otavioburato42@gmail.com
License: UNKNOWN
Platform: UNKNOWN
Requires-Python: >=3.8
